odoo9_addon_stock_move_partner_info-9.0.1.0.0-py2.7-nspkg.pth
odoo9_addon_stock_move_partner_info-9.0.1.0.0.dist-info/DESCRIPTION.rst
odoo9_addon_stock_move_partner_info-9.0.1.0.0.dist-info/METADATA
odoo9_addon_stock_move_partner_info-9.0.1.0.0.dist-info/RECORD
odoo9_addon_stock_move_partner_info-9.0.1.0.0.dist-info/WHEEL
odoo9_addon_stock_move_partner_info-9.0.1.0.0.dist-info/metadata.json
odoo9_addon_stock_move_partner_info-9.0.1.0.0.dist-info/namespace_packages.txt
odoo9_addon_stock_move_partner_info-9.0.1.0.0.dist-info/top_level.txt
odoo_addons/stock_move_partner_info/README.rst
odoo_addons/stock_move_partner_info/__init__.py
odoo_addons/stock_move_partner_info/__openerp__.py
odoo_addons/stock_move_partner_info/i18n/es.po
odoo_addons/stock_move_partner_info/i18n/pt_BR.po
odoo_addons/stock_move_partner_info/i18n/sl.po
odoo_addons/stock_move_partner_info/models/__init__.py
odoo_addons/stock_move_partner_info/models/stock_move.py
odoo_addons/stock_move_partner_info/views/stock_move_view.xml
